housemodel/__init__.py
housemodel/constants.py
housemodel/for_companies_solver.py
housemodel/heat_pump_solver.py
housemodel/simulation.py
housemodel/basics/__init__.py
housemodel/basics/ckf_tools.py
housemodel/basics/components.py
housemodel/basics/flows.py
housemodel/basics/house.py
housemodel/basics/powersource.py
housemodel/basics/source_term.py
housemodel/basics/totalsystem.py
housemodel/buildings/Simulation_house_buffer_nodes_and_edges.py
housemodel/buildings/__init__.py
housemodel/buildings/building.py
housemodel/controls/Temperature_SP.py
housemodel/controls/__init__.py
housemodel/controls/heating_curves.py
housemodel/controls/ivPID/PID.py
housemodel/controls/ivPID/__init__.py
housemodel/controls/ivPID/test_pid.py
housemodel/finite_elements/__init__.py
housemodel/finite_elements/ckf_elements_xl.py
housemodel/solvers/Apartment_model_WHATAS.py
housemodel/solvers/Apartment_model_WHATAS_scenario2.py
housemodel/solvers/Office_model_WHATAS.py
housemodel/solvers/__init__.py
housemodel/solvers/house_model_for_companies.py
housemodel/solvers/house_model_for_companies_ne.py
housemodel/solvers/house_model_heat_pump_NTA8800.py
housemodel/solvers/house_model_heat_pump_NTA8800_ne.py
housemodel/solvers/house_model_heat_pump_NTA8800_part_load.py
housemodel/solvers/house_model_heat_pump_NTA8800_with_buffervessel.py
housemodel/solvers/house_model_with_HeatingSystemClass.py
housemodel/sourcesink/NEN5060.py
housemodel/sourcesink/PV_panel.py
housemodel/sourcesink/__init__.py
housemodel/sourcesink/colab_pid.py
housemodel/sourcesink/heatexchangers.py
housemodel/sourcesink/internal_heat_gain.py
housemodel/sourcesink/qsun.py
housemodel/sourcesink/boilers/__init__.py
housemodel/sourcesink/boilers/boilers.py
housemodel/sourcesink/boilers/boilers_without_PID.py
housemodel/sourcesink/buffervessels/__init__.py
housemodel/sourcesink/buffervessels/buffer_vessel.py
housemodel/sourcesink/buffervessels/stratified.py
housemodel/sourcesink/radiators/__init__.py
housemodel-0.0.2.dist-info/LICENSE
housemodel-0.0.2.dist-info/METADATA
housemodel-0.0.2.dist-info/WHEEL
housemodel-0.0.2.dist-info/top_level.txt
housemodel-0.0.2.dist-info/RECORD
