Metadata-Version: 2.1
Name: housemodel
Version: 0.0.2
Summary: HAN Open Source House Model
Author-email: "Paul J.M. van Kan" <paul.vankan@han.nl>
Project-URL: Homepage, https://github.com/hancse/twozone_housemodel
Classifier: Programming Language :: Python :: 3
Classifier: License :: OSI Approved :: GNU General Public License v3 or later (GPLv3+)
Classifier: Operating System :: OS Independent
Requires-Python: >=3.8
License-File: LICENSE
